src/__init__.py
src/__pycache__/__init__.cpython-311.pyc
src/main/__init__.py
src/main/dates.py
src/main/filehelper.py
src/main/logger.py
src/main/secrets.py
src/main/__pycache__/__init__.cpython-311.pyc
src/main/__pycache__/dates.cpython-311.pyc
src/main/data_tools/__init__.py
src/main/data_tools/database.py
src/main/data_tools/dataframes.py
src/main/data_tools/schemas.py
src/main/loads/Load.py
src/main/loads/LoadStep.py
src/main/loads/Reader.py
src/main/loads/Writer.py
src/main/loads/__init__.py
src/main/loads/helpers.py
src/main/rest_apis/Request.py
src/main/rest_apis/RequestHandler.py
src/main/rest_apis/RequestParameters.py
src/main/rest_apis/RequestQueue.py
src/main/rest_apis/__init__.py
src/test/__init__.py
src/test/test_dates.py
src/test/__pycache__/__init__.cpython-311.pyc
src/test/__pycache__/test_dates.cpython-311-pytest-7.3.1.pyc
jhdata-1.0.64.dist-info/LICENSE
jhdata-1.0.64.dist-info/METADATA
jhdata-1.0.64.dist-info/WHEEL
jhdata-1.0.64.dist-info/top_level.txt
jhdata-1.0.64.dist-info/RECORD
