Metadata-Version: 2.1
Name: jhdata
Version: 1.0.64
Summary: Abstractions around cloud file interfaces (WIP)
Home-page: https://github.com/jothapunkt/jhdata
Author: Jothapunkt
Author-email: jakob-hoefner@web.de
Requires-Python: >=3.8
License-File: LICENSE
Requires-Dist: requests
Requires-Dist: boto3
Requires-Dist: s3fs
Requires-Dist: pandas
Requires-Dist: pyarrow
Requires-Dist: sqlalchemy
Requires-Dist: psycopg2
Requires-Dist: pandera[io]
Requires-Dist: aioitertools
Requires-Dist: pyrsistent
